operations/alu_rshift.sv
module alu_rshift (
    input  logic [7:0] A,          // 8-bit Operand A
    input  logic [7:0] B,          // 8-bit Shift Amount (A is shifted right by B positions)
    output logic [7:0] Result,     // 8-bit Result
    output logic       Z,          // Zero Flag
    output logic       N,          // Negative Flag
    output logic       V           // Overflow Flag
);

    logic [7:0] rshift_result;

    // Logical Right Shift by B Combinational Logic
    always_comb begin
        if (B >= 8)
            rshift_result = 8'b0;   // shifting an 8-bit value by 8+ moves every bit out
        else
            rshift_result = A >> B;
    end

    // Output assignment
    assign Result = rshift_result;

    // Flag calculations
    assign Z = (rshift_result == 8'b0);
    assign N = rshift_result[7];  // MSB indicates negative in two's complement
    assign V = 1'b0;              // No overflow for shift operation

endmodule

operations/alu_lshift.sv
module alu_lshift (
    input  logic [7:0] A,          // 8-bit Operand A
    input  logic [7:0] B,          // 8-bit Shift Amount (A is shifted left by B positions)
    output logic [7:0] Result,     // 8-bit Result
    output logic       Z,          // Zero Flag
    output logic       N,          // Negative Flag
    output logic       V           // Overflow Flag
);

    logic [7:0] lshift_result;

    // Logical Left Shift by B Combinational Logic
    always_comb begin
        if (B >= 8)
            lshift_result = 8'b0;   // shifting an 8-bit value by 8+ moves every bit out
        else
            lshift_result = A << B;
    end

    // Output assignment
    assign Result = lshift_result;

    // Flag calculations
    assign Z = (lshift_result == 8'b0);
    assign N = lshift_result[7];  // MSB indicates negative in two's complement
    assign V = 1'b0;              // No overflow for shift operation

endmodule

operations/alu_xor.sv
module alu_xor (
    input  logic [7:0] A,          // 8-bit Operand A
    input  logic [7:0] B,          // 8-bit Operand B
    output logic [7:0] Result,     // 8-bit Result
    output logic       Z,          // Zero Flag
    output logic       N,          // Negative Flag
    output logic       V           // Overflow Flag
);

    logic [7:0] xor_result;

    // Bitwise XOR Combinational Logic
    always_comb begin
        xor_result = A ^ B;
    end

    // Output assignment
    assign Result = xor_result;

    // Flag calculations
    assign Z = (xor_result == 8'b0);
    assign N = xor_result[7];     // MSB indicates negative in two's complement
    assign V = 1'b0;              // No overflow for XOR operation

endmodule

operations/alu_or.sv
module alu_or (
    input  logic [7:0] A,          // 8-bit Operand A
    input  logic [7:0] B,          // 8-bit Operand B
    output logic [7:0] Result,     // 8-bit Result
    output logic       Z,          // Zero Flag
    output logic       N,          // Negative Flag
    output logic       V           // Overflow Flag
);

    logic [7:0] or_result;

    // Bitwise OR Combinational Logic
    always_comb begin
        or_result = A | B;
    end

    // Output assignment
    assign Result = or_result;

    // Flag calculations
    assign Z = (or_result == 8'b0);
    assign N = or_result[7];      // MSB indicates negative in two's complement
    assign V = 1'b0;              // No overflow for OR operation

endmodule

operations/alu_and.sv
module alu_and (
    input  logic [7:0] A,          // 8-bit Operand A
    input  logic [7:0] B,          // 8-bit Operand B
    output logic [7:0] Result,     // 8-bit Result
    output logic       Z,          // Zero Flag
    output logic       N,          // Negative Flag
    output logic       V           // Overflow Flag
);

    logic [7:0] and_result;

    // Bitwise AND Combinational Logic
    always_comb begin
        and_result = A & B;
    end

    // Output assignment
    assign Result = and_result;

    // Flag calculations
    assign Z = (and_result == 8'b0);
    assign N = and_result[7];     // MSB indicates negative in two's complement
    assign V = 1'b0;              // No overflow for AND operation

endmodule

operations/alu_div.sv
module alu_div (
    input  logic [7:0] A,          // 8-bit Dividend
    input  logic [7:0] B,          // 8-bit Divisor
    output logic [7:0] Result,     // 8-bit Result
    output logic       Z,          // Zero Flag
    output logic       N,          // Negative Flag
    output logic       V           // Overflow Flag
);

    logic [7:0] div_result;

    // Division Combinational Logic
    always_comb begin
        if (B != 0) 
            div_result = A / B;
        else 
            div_result = 8'b0;    // Safe divide-by-zero fallback
    end

    // Output assignment
    assign Result = div_result;

    // Flag calculations
    assign Z = (div_result == 8'b0);
    assign N = div_result[7];     // MSB indicates negative in two's complement
    assign V = 1'b0;              // No overflow for division

endmodule

operations/alu_mult.sv
module alu_mult (
    input  logic [7:0] A, // 8-bit Multiplicand
    input  logic [7:0] B, // 8-bit Multiplier
    output logic [7:0] Result, // 8-bit (truncated) Result
    output logic Z, // Zero Flag
    output logic N, // Negative Flag (MSB of truncated result)
    output logic V // "Overflow" Flag - in this case checks if the product truncated on 8 bits lost real information
);
    logic [15:0] mult_wide; // full-width product, avoids implicit truncation
    logic [7:0]  mult_result; // low byte of the product, what gets output

    // Multiplication Combinational Logic
    always_comb begin
        mult_wide = A * B; // full 16-bit unsigned product
        mult_result = mult_wide[7:0];
    end

    // Output assignment
    assign Result = mult_result;

    // Flag calculations
    assign Z = (mult_result == 8'b0);
    assign N = mult_result[7]; // MSB of the truncated byte
    assign V = (mult_wide[15:8] != 8'b0); // true product didn't fit in 8 bits
endmodule

operations/alu_subtract.sv
module alu_subtract (
    input logic [7:0] A, // 8-bit Minuend
    input logic [7:0] B, // 8-bit Subtrahend
    output logic [7:0] Result, // 8-bit Result
    output logic Z, // Zero Flag
    output logic N, // Negative Flag (MSB of result)
    output logic C, // Borrow Flag (unsigned underflow, A < B)
    output logic V // Overflow Flag (signed overflow)
);
    logic [7:0] sub_result;

    // Subtraction Combinational Logic
    always_comb begin
        sub_result = A - B;
    end

    // Output assignment
    assign Result = sub_result;

    // Flag calculations
    assign Z = (sub_result == 8'b0);
    assign N = sub_result[7];
    assign C = (A < B); // borrow occurred, A could not cover B
    assign V = (A[7] != B[7]) && (sub_result[7] != A[7]); // signed overflow
    
endmodule

operations/alu_add.sv
module alu_add (
    input logic [7:0] A,
    input logic [7:0] B,
    output logic [7:0] Result,
    output logic Z, // Zero Flag
    output logic N, // Negative Flag
    output logic C, // Carry out
    output logic V // Overflow Flag
);
    logic [8:0] sum_wide; // sum_wide on 9 bits to account for possible carry out
    logic [7:0] add_result;

    always_comb begin
        sum_wide   = {1'b0, A} + {1'b0, B}; // 
        add_result = sum_wide[7:0];
    end

    assign Result = add_result;
    assign Z = (add_result == 8'b0);
    assign N = add_result[7];
    assign C = sum_wide[8];
    assign V = (A[7] == B[7]) && (add_result[7] != A[7]); // sign bits of A and B are the same and sign bit of result is different
    
endmodule

alu_8bit_top.sv
module alu_8bit_top (
    input  logic [7:0] A,          // 8-bit Operand A
    input  logic [7:0] B,          // 8-bit Operand B
    input  logic [3:0] ALU_Sel,    // 4-bit Operation Selector
    output logic [7:0] Result,     // 8-bit Result
    output logic       Z,          // Zero Flag
    output logic       N,          // Negative Flag
    output logic       V           // Overflow Flag
);

    logic [7:0] add_result, sub_result, mult_result, div_result, and_result, or_result, xor_result, lshift_result, rshift_result;
    logic add_z, add_n, add_c, add_v;
    logic sub_z, sub_n, sub_c, sub_v;
    logic mult_z, mult_n, mult_v;
    logic div_z, div_n, div_v;
    logic and_z, and_n, and_v;
    logic or_z, or_n, or_v;
    logic xor_z, xor_n, xor_v;
    logic lshift_z, lshift_n, lshift_v;
    logic rshift_z, rshift_n, rshift_v;

    // Instantiate Addition Module
    alu_add add_inst (
        .A(A),
        .B(B),
        .Result(add_result),
        .Z(add_z),
        .N(add_n),
        .C(add_c),      // carry out - computed but not surfaced at this module's interface
        .V(add_v)
    );

    // Instantiate Subtraction Module
    alu_subtract sub_inst (
        .A(A),
        .B(B),
        .Result(sub_result),
        .Z(sub_z),
        .N(sub_n),
        .C(sub_c),      // borrow flag - computed but not surfaced at this module's interface
        .V(sub_v)
    );

    // Instantiate Multiplication Module
    alu_mult mult_inst (
        .A(A),
        .B(B),
        .Result(mult_result),
        .Z(mult_z),
        .N(mult_n),
        .V(mult_v)      // truncation-overflow flag, defined by alu_mult itself
    );

    // Instantiate Division Module
    alu_div div_inst (
        .A(A),
        .B(B),
        .Result(div_result),
        .Z(div_z),
        .N(div_n),
        .V(div_v)
    );

    // Instantiate AND Module
    alu_and and_inst (
        .A(A),
        .B(B),
        .Result(and_result),
        .Z(and_z),
        .N(and_n),
        .V(and_v)
    );

    // Instantiate OR Module
    alu_or or_inst (
        .A(A),
        .B(B),
        .Result(or_result),
        .Z(or_z),
        .N(or_n),
        .V(or_v)
    );

    // Instantiate XOR Module
    alu_xor xor_inst (
        .A(A),
        .B(B),
        .Result(xor_result),
        .Z(xor_z),
        .N(xor_n),
        .V(xor_v)
    );

    // Instantiate Left Shift Module
    alu_lshift lshift_inst (
        .A(A),
        .B(B),
        .Result(lshift_result),
        .Z(lshift_z),
        .N(lshift_n),
        .V(lshift_v)
    );

    // Instantiate Right Shift Module
    alu_rshift rshift_inst (
        .A(A),
        .B(B),
        .Result(rshift_result),
        .Z(rshift_z),
        .N(rshift_n),
        .V(rshift_v)
    );

    // Multiplexer for Result Selection
    always_comb begin
        case (ALU_Sel)
            4'b0000: begin
                Result = add_result;
                Z = add_z;
                N = add_n;
                V = add_v;
            end
            4'b0001: begin
                Result = sub_result;
                Z = sub_z;
                N = sub_n;
                V = sub_v;
            end
            4'b0010: begin
                Result = mult_result;
                Z = mult_z;
                N = mult_n;
                V = mult_v;
            end
            4'b0011: begin
                Result = div_result;
                Z = div_z;
                N = div_n;
                V = div_v;
            end
            4'b0100: begin
                Result = and_result;
                Z = and_z;
                N = and_n;
                V = and_v;
            end
            4'b0101: begin
                Result = or_result;
                Z = or_z;
                N = or_n;
                V = or_v;
            end
            4'b0110: begin
                Result = xor_result;
                Z = xor_z;
                N = xor_n;
                V = xor_v;
            end
            4'b0111: begin
                Result = lshift_result;
                Z = lshift_z;
                N = lshift_n;
                V = lshift_v;
            end
            4'b1000: begin
                Result = rshift_result;
                Z = rshift_z;
                N = rshift_n;
                V = rshift_v;
            end
            default: begin
                Result = 8'b0;
                Z = 1'b0;
                N = 1'b0;
                V = 1'b0;
            end
        endcase
    end

endmodule

tb_alu_top.sv
module tb_alu_top;

    // Testbench signals
    logic [7:0] A;
    logic [7:0] B;
    logic [3:0] ALU_Sel;
    logic [7:0] Result;
    logic       Z;
    logic       N;
    logic       V;

    // Instantiate the modular ALU (Device Under Test)
    alu_8bit_top dut (
        .A(A),
        .B(B),
        .ALU_Sel(ALU_Sel),
        .Result(Result),
        .Z(Z),
        .N(N),
        .V(V)
    );

    // Test sequence - mirrors tb_alu.sv so the monolithic and modular
    // implementations can be checked against the same vectors.
    initial begin
        // Setup waveform dumping for GTKWave
        $dumpfile("tb_alu_top.vcd");
        $dumpvars(0, tb_alu_top);

        $display("Starting ALU (modular) Simulation...");
        $display("--------------------------------------------------");
        $display(" A    | B    | Sel | Result | Z | N | V | Operation");
        $display("--------------------------------------------------");

        // 0. Addition (Normal)
        A = 8'd50; B = 8'd25; ALU_Sel = 4'b0000; #10;
        $display("%4d | %4d | %b | %6d | %b | %b | %b | Addition", A, B, ALU_Sel, Result, Z, N, V);

        // 0. Addition (Overflow Trigger: 127 + 1 = 128 -> -128 in signed 8-bit)
        A = 8'd127; B = 8'd1; ALU_Sel = 4'b0000; #10;
        $display("%4d | %4d | %b | %6d | %b | %b | %b | Add (Overflow)", A, B, ALU_Sel, $signed(Result), Z, N, V);

        // 1. Subtraction
        A = 8'd100; B = 8'd20; ALU_Sel = 4'b0001; #10;
        $display("%4d | %4d | %b | %6d | %b | %b | %b | Subtraction", A, B, ALU_Sel, Result, Z, N, V);

        // 2. Multiplication
        A = 8'd10; B = 8'd5; ALU_Sel = 4'b0010; #10;
        $display("%4d | %4d | %b | %6d | %b | %b | %b | Multiplication", A, B, ALU_Sel, Result, Z, N, V);

        // 2. Multiplication (Truncation: 200 * 2 = 400, doesn't fit in 8 bits)
        A = 8'd200; B = 8'd2; ALU_Sel = 4'b0010; #10;
        $display("%4d | %4d | %b | %6d | %b | %b | %b | Mult (Truncate)", A, B, ALU_Sel, Result, Z, N, V);

        // 3. Division
        A = 8'd100; B = 8'd10; ALU_Sel = 4'b0011; #10;
        $display("%4d | %4d | %b | %6d | %b | %b | %b | Division", A, B, ALU_Sel, Result, Z, N, V);

        // 3. Division by Zero
        A = 8'd50; B = 8'd0; ALU_Sel = 4'b0011; #10;
        $display("%4d | %4d | %b | %6d | %b | %b | %b | Div by Zero", A, B, ALU_Sel, Result, Z, N, V);

        // 4. Bitwise AND
        A = 8'b11110000; B = 8'b10101010; ALU_Sel = 4'b0100; #10;
        $display("%b | %b | %b | %b | %b | %b | %b | AND", A, B, ALU_Sel, Result, Z, N, V);

        // 5. Bitwise OR
        A = 8'b11110000; B = 8'b00001111; ALU_Sel = 4'b0101; #10;
        $display("%b | %b | %b | %b | %b | %b | %b | OR", A, B, ALU_Sel, Result, Z, N, V);

        // 6. Bitwise XOR
        A = 8'b11110000; B = 8'b11111111; ALU_Sel = 4'b0110; #10;
        $display("%b | %b | %b | %b | %b | %b | %b | XOR", A, B, ALU_Sel, Result, Z, N, V);

        // 7. Left Shift by 3
        A = 8'b00001111; B = 8'd3; ALU_Sel = 4'b0111; #10;
        $display("%b | %4d | %b | %b | %b | %b | %b | Left Shift (by 3)", A, B, ALU_Sel, Result, Z, N, V);

        // 7. Left Shift by 0 (no movement)
        A = 8'b00001111; B = 8'd0; ALU_Sel = 4'b0111; #10;
        $display("%b | %4d | %b | %b | %b | %b | %b | Left Shift (by 0)", A, B, ALU_Sel, Result, Z, N, V);

        // 7. Left Shift by >= 8 (every bit shifted out -> 0)
        A = 8'b00001111; B = 8'd9; ALU_Sel = 4'b0111; #10;
        $display("%b | %4d | %b | %b | %b | %b | %b | Left Shift (B>=8)", A, B, ALU_Sel, Result, Z, N, V);

        // 8. Right Shift by 3
        A = 8'b11110000; B = 8'd3; ALU_Sel = 4'b1000; #10;
        $display("%b | %4d | %b | %b | %b | %b | %b | Right Shift (by 3)", A, B, ALU_Sel, Result, Z, N, V);

        // 8. Right Shift by 0 (no movement)
        A = 8'b11110000; B = 8'd0; ALU_Sel = 4'b1000; #10;
        $display("%b | %4d | %b | %b | %b | %b | %b | Right Shift (by 0)", A, B, ALU_Sel, Result, Z, N, V);

        // 8. Right Shift by exactly 8 (every bit shifted out -> 0)
        A = 8'b11110000; B = 8'd8; ALU_Sel = 4'b1000; #10;
        $display("%b | %4d | %b | %b | %b | %b | %b | Right Shift (B==8)", A, B, ALU_Sel, Result, Z, N, V);

        $display("--------------------------------------------------");
        $display("Simulation Complete.");

        $finish; // End simulation
    end

endmodule

sim/tb_alu_top.vcd
$date
	Thu Jun 18 01:22:28 2026
$end
$version
	Icarus Verilog
$end
$timescale
	1s
$end
$scope module tb_alu_top $end
$var wire 1 ! Z $end
$var wire 1 " V $end
$var wire 8 # Result [7:0] $end
$var wire 1 $ N $end
$var reg 8 % A [7:0] $end
$var reg 4 & ALU_Sel [3:0] $end
$var reg 8 ' B [7:0] $end
$scope module dut $end
$var wire 8 ( A [7:0] $end
$var wire 4 ) ALU_Sel [3:0] $end
$var wire 8 * B [7:0] $end
$var wire 1 + and_v $end
$var wire 1 , div_v $end
$var wire 1 - lshift_v $end
$var wire 1 . or_v $end
$var wire 1 / rshift_v $end
$var wire 1 0 xor_v $end
$var wire 1 1 xor_z $end
$var wire 8 2 xor_result [7:0] $end
$var wire 1 3 xor_n $end
$var wire 1 4 sub_z $end
$var wire 1 5 sub_v $end
$var wire 8 6 sub_result [7:0] $end
$var wire 1 7 sub_n $end
$var wire 1 8 sub_c $end
$var wire 1 9 rshift_z $end
$var wire 8 : rshift_result [7:0] $end
$var wire 1 ; rshift_n $end
$var wire 1 < or_z $end
$var wire 8 = or_result [7:0] $end
$var wire 1 > or_n $end
$var wire 1 ? mult_z $end
$var wire 1 @ mult_v $end
$var wire 8 A mult_result [7:0] $end
$var wire 1 B mult_n $end
$var wire 1 C lshift_z $end
$var wire 8 D lshift_result [7:0] $end
$var wire 1 E lshift_n $end
$var wire 1 F div_z $end
$var wire 8 G div_result [7:0] $end
$var wire 1 H div_n $end
$var wire 1 I and_z $end
$var wire 8 J and_result [7:0] $end
$var wire 1 K and_n $end
$var wire 1 L add_z $end
$var wire 1 M add_v $end
$var wire 8 N add_result [7:0] $end
$var wire 1 O add_n $end
$var wire 1 P add_c $end
$var reg 1 $ N $end
$var reg 8 Q Result [7:0] $end
$var reg 1 " V $end
$var reg 1 ! Z $end
$scope module add_inst $end
$var wire 8 R A [7:0] $end
$var wire 8 S B [7:0] $end
$var wire 8 T Result [7:0] $end
$var wire 1 M V $end
$var wire 1 L Z $end
$var wire 1 O N $end
$var wire 1 P C $end
$var reg 8 U add_result [7:0] $end
$var reg 9 V sum_wide [8:0] $end
$upscope $end
$scope module and_inst $end
$var wire 8 W A [7:0] $end
$var wire 8 X B [7:0] $end
$var wire 8 Y Result [7:0] $end
$var wire 1 + V $end
$var wire 1 I Z $end
$var wire 1 K N $end
$var reg 8 Z and_result [7:0] $end
$upscope $end
$scope module div_inst $end
$var wire 8 [ A [7:0] $end
$var wire 8 \ B [7:0] $end
$var wire 8 ] Result [7:0] $end
$var wire 1 , V $end
$var wire 1 F Z $end
$var wire 1 H N $end
$var reg 8 ^ div_result [7:0] $end
$upscope $end
$scope module lshift_inst $end
$var wire 8 _ A [7:0] $end
$var wire 8 ` B [7:0] $end
$var wire 8 a Result [7:0] $end
$var wire 1 - V $end
$var wire 1 C Z $end
$var wire 1 E N $end
$var reg 8 b lshift_result [7:0] $end
$upscope $end
$scope module mult_inst $end
$var wire 8 c A [7:0] $end
$var wire 8 d B [7:0] $end
$var wire 8 e Result [7:0] $end
$var wire 1 ? Z $end
$var wire 1 @ V $end
$var wire 1 B N $end
$var reg 8 f mult_result [7:0] $end
$var reg 16 g mult_wide [15:0] $end
$upscope $end
$scope module or_inst $end
$var wire 8 h A [7:0] $end
$var wire 8 i B [7:0] $end
$var wire 8 j Result [7:0] $end
$var wire 1 . V $end
$var wire 1 < Z $end
$var wire 1 > N $end
$var reg 8 k or_result [7:0] $end
$upscope $end
$scope module rshift_inst $end
$var wire 8 l A [7:0] $end
$var wire 8 m B [7:0] $end
$var wire 8 n Result [7:0] $end
$var wire 1 / V $end
$var wire 1 9 Z $end
$var wire 1 ; N $end
$var reg 8 o rshift_result [7:0] $end
$upscope $end
$scope module sub_inst $end
$var wire 8 p A [7:0] $end
$var wire 8 q B [7:0] $end
$var wire 8 r Result [7:0] $end
$var wire 1 5 V $end
$var wire 1 4 Z $end
$var wire 1 7 N $end
$var wire 1 8 C $end
$var reg 8 s sub_result [7:0] $end
$upscope $end
$scope module xor_inst $end
$var wire 8 t A [7:0] $end
$var wire 8 u B [7:0] $end
$var wire 8 v Result [7:0] $end
$var wire 1 0 V $end
$var wire 1 1 Z $end
$var wire 1 3 N $end
$var reg 8 w xor_result [7:0] $end
$upscope $end
$upscope $end
$upscope $end
$enddefinitions $end
$comment Show the parameter values. $end
$dumpall
$end
#0
$dumpvars
b101011 w
b101011 v
b11001 u
b110010 t
b11001 s
b11001 r
b11001 q
b110010 p
b0 o
b0 n
b11001 m
b110010 l
b111011 k
b111011 j
b11001 i
b110010 h
b10011100010 g
b11100010 f
b11100010 e
b11001 d
b110010 c
b0 b
b0 a
b11001 `
b110010 _
b10 ^
b10 ]
b11001 \
b110010 [
b10000 Z
b10000 Y
b11001 X
b110010 W
b1001011 V
b1001011 U
b1001011 T
b11001 S
b110010 R
b1001011 Q
0P
0O
b1001011 N
0M
0L
0K
b10000 J
0I
0H
b10 G
0F
0E
b0 D
1C
1B
b11100010 A
1@
0?
0>
b111011 =
0<
0;
b0 :
19
08
07
b11001 6
05
04
03
b101011 2
01
00
0/
0.
0-
0,
0+
b11001 *
b0 )
b110010 (
b11001 '
b0 &
b110010 %
0$
b1001011 #
0"
0!
$end
#10
1"
1M
1$
1O
1E
0B
b10000000 #
b10000000 Q
0@
b10000000 N
b10000000 T
b10000000 U
b10000000 V
b1111110 6
b1111110 r
b1111110 s
b1 J
b1 Y
b1 Z
b1111111 =
b1111111 j
b1111111 k
b1111110 2
b1111110 v
b1111110 w
b1111111 G
b1111111 ]
b1111111 ^
0C
b11111110 D
b11111110 a
b11111110 b
09
b111111 :
b111111 n
b111111 o
b1111111 A
b1111111 e
b1111111 f
b1111111 g
b1 '
b1 *
b1 S
b1 X
b1 \
b1 `
b1 d
b1 i
b1 m
b1 q
b1 u
b1111111 %
b1111111 (
b1111111 R
b1111111 W
b1111111 [
b1111111 _
b1111111 c
b1111111 h
b1111111 l
b1111111 p
b1111111 t
#20
0M
0O
0E
1B
1@
0"
0$
b1010000 #
b1010000 Q
b1111000 N
b1111000 T
b1111000 U
b1111000 V
b1010000 6
b1010000 r
b1010000 s
b100 J
b100 Y
b100 Z
b1110100 =
b1110100 j
b1110100 k
b1110000 2
b1110000 v
b1110000 w
b101 G
b101 ]
b101 ^
1C
b0 D
b0 a
b0 b
19
b0 :
b0 n
b0 o
b11010000 A
b11010000 e
b11010000 f
b11111010000 g
b1 &
b1 )
b10100 '
b10100 *
b10100 S
b10100 X
b10100 \
b10100 `
b10100 d
b10100 i
b10100 m
b10100 q
b10100 u
b1100100 %
b1100100 (
b1100100 R
b1100100 W
b1100100 [
b1100100 _
b1100100 c
b1100100 h
b1100100 l
b1100100 p
b1100100 t
#30
0B
0@
0"
0$
b110010 #
b110010 Q
b1111 N
b1111 T
b1111 U
b1111 V
b101 6
b101 r
b101 s
1I
b0 J
b0 Y
b0 Z
b1111 =
b1111 j
b1111 k
b1111 2
b1111 v
b1111 w
b10 G
b10 ]
b10 ^
0C
b1000000 D
b1000000 a
b1000000 b
b110010 A
b110010 e
b110010 f
b110010 g
b10 &
b10 )
b101 '
b101 *
b101 S
b101 X
b101 \
b101 `
b101 d
b101 i
b101 m
b101 q
b101 u
08
b1010 %
b1010 (
b1010 R
b1010 W
b1010 [
b1010 _
b1010 c
b1010 h
b1010 l
b1010 p
b1010 t
#40
1$
05
1O
17
1>
13
1B
1"
b10010000 #
b10010000 Q
1@
b11001010 N
b11001010 T
b11001010 U
b11001010 V
b11000110 6
b11000110 r
b11000110 s
b11001010 =
b11001010 j
b11001010 k
b11001010 2
b11001010 v
b11001010 w
b1100100 G
b1100100 ]
b1100100 ^
b100000 D
b100000 a
b100000 b
09
b110010 :
b110010 n
b110010 o
b10010000 A
b10010000 e
b10010000 f
b110010000 g
b10 '
b10 *
b10 S
b10 X
b10 \
b10 `
b10 d
b10 i
b10 m
b10 q
b10 u
b11001000 %
b11001000 (
b11001000 R
b11001000 W
b11001000 [
b11001000 _
b11001000 c
b11001000 h
b11001000 l
b11001000 p
b11001000 t
#50
0M
0O
07
0>
03
0"
0$
b1010 #
b1010 Q
b1101110 N
b1101110 T
b1101110 U
b1101110 V
b1011010 6
b1011010 r
b1011010 s
b1101110 =
b1101110 j
b1101110 k
b1101110 2
b1101110 v
b1101110 w
b1010 G
b1010 ]
b1010 ^
1C
b0 D
b0 a
b0 b
19
b0 :
b0 n
b0 o
b11101000 A
b11101000 e
b11101000 f
b1111101000 g
b11 &
b11 )
b1010 '
b1010 *
b1010 S
b1010 X
b1010 \
b1010 `
b1010 d
b1010 i
b1010 m
b1010 q
b1010 u
b1100100 %
b1100100 (
b1100100 R
b1100100 W
b1100100 [
b1100100 _
b1100100 c
b1100100 h
b1100100 l
b1100100 p
b1100100 t
#60
0B
1!
b0 #
b0 Q
0@
b110010 N
b110010 T
b110010 U
b110010 V
b110010 6
b110010 r
b110010 s
b110010 =
b110010 j
b110010 k
b110010 2
b110010 v
b110010 w
1F
b0 G
b0 ]
b0 ^
0C
b110010 D
b110010 a
b110010 b
09
b110010 :
b110010 n
b110010 o
1?
b0 A
b0 e
b0 f
b0 g
b0 '
b0 *
b0 S
b0 X
b0 \
b0 `
b0 d
b0 i
b0 m
b0 q
b0 u
b110010 %
b110010 (
b110010 R
b110010 W
b110010 [
b110010 _
b110010 c
b110010 h
b110010 l
b110010 p
b110010 t
#70
0M
1$
1O
1P
1K
1>
1@
0!
b10100000 #
b10100000 Q
b10011010 N
b10011010 T
b10011010 U
b110011010 V
b1000110 6
b1000110 r
b1000110 s
0I
b10100000 J
b10100000 Y
b10100000 Z
b11111010 =
b11111010 j
b11111010 k
b1011010 2
b1011010 v
b1011010 w
0F
b1 G
b1 ]
b1 ^
1C
b0 D
b0 a
b0 b
19
b0 :
b0 n
b0 o
0?
b1100000 A
b1100000 e
b1100000 f
b1001111101100000 g
b100 &
b100 )
b10101010 '
b10101010 *
b10101010 S
b10101010 X
b10101010 \
b10101010 `
b10101010 d
b10101010 i
b10101010 m
b10101010 q
b10101010 u
b11110000 %
b11110000 (
b11110000 R
b11110000 W
b11110000 [
b11110000 _
b11110000 c
b11110000 h
b11110000 l
b11110000 p
b11110000 t
#80
05
0P
17
0K
13
b11111111 #
b11111111 Q
b11111111 N
b11111111 T
b11111111 U
b11111111 V
b11100001 6
b11100001 r
b11100001 s
1I
b0 J
b0 Y
b0 Z
b11111111 =
b11111111 j
b11111111 k
b11111111 2
b11111111 v
b11111111 w
b10000 G
b10000 ]
b10000 ^
b10000 A
b10000 e
b10000 f
b111000010000 g
b101 &
b101 )
b1111 '
b1111 *
b1111 S
b1111 X
b1111 \
b1111 `
b1111 d
b1111 i
b1111 m
b1111 q
b1111 u
#90
0$
1P
1K
03
b1111 #
b1111 Q
b11101111 N
b11101111 T
b11101111 U
b111101111 V
b11110001 6
b11110001 r
b11110001 s
0I
b11110000 J
b11110000 Y
b11110000 Z
b1111 2
b1111 v
b1111 w
1F
b0 G
b0 ]
b0 ^
b1110111100010000 g
b110 &
b110 )
18
b11111111 '
b11111111 *
b11111111 S
b11111111 X
b11111111 \
b11111111 `
b11111111 d
b11111111 i
b11111111 m
b11111111 q
b11111111 u
#100
0M
0O
0P
07
0K
0>
0@
b1111000 #
b1111000 Q
b10010 N
b10010 T
b10010 U
b10010 V
b1100 6
b1100 r
b1100 s
b11 J
b11 Y
b11 Z
b1111 =
b1111 j
b1111 k
b1100 2
b1100 v
b1100 w
0F
b101 G
b101 ]
b101 ^
0C
b1111000 D
b1111000 a
b1111000 b
09
b1 :
b1 n
b1 o
b101101 A
b101101 e
b101101 f
b101101 g
b111 &
b111 )
08
b11 '
b11 *
b11 S
b11 X
b11 \
b11 `
b11 d
b11 i
b11 m
b11 q
b11 u
b1111 %
b1111 (
b1111 R
b1111 W
b1111 [
b1111 _
b1111 c
b1111 h
b1111 l
b1111 p
b1111 t
#110
b1111 #
b1111 Q
b1111 N
b1111 T
b1111 U
b1111 V
b1111 6
b1111 r
b1111 s
1I
b0 J
b0 Y
b0 Z
b1111 2
b1111 v
b1111 w
1F
b0 G
b0 ]
b0 ^
b1111 D
b1111 a
b1111 b
b1111 :
b1111 n
b1111 o
1?
b0 A
b0 e
b0 f
b0 g
b0 '
b0 *
b0 S
b0 X
b0 \
b0 `
b0 d
b0 i
b0 m
b0 q
b0 u
#120
1B
1!
b0 #
b0 Q
b11000 N
b11000 T
b11000 U
b11000 V
b110 6
b110 r
b110 s
0I
b1001 J
b1001 Y
b1001 Z
b110 2
b110 v
b110 w
0F
b1 G
b1 ]
b1 ^
1C
b0 D
b0 a
b0 b
19
b0 :
b0 n
b0 o
0?
b10000111 A
b10000111 e
b10000111 f
b10000111 g
b1001 '
b1001 *
b1001 S
b1001 X
b1001 \
b1001 `
b1001 d
b1001 i
b1001 m
b1001 q
b1001 u
#130
05
1O
17
1>
13
1E
1@
0!
b11110 #
b11110 Q
b11110011 N
b11110011 T
b11110011 U
b11110011 V
b11101101 6
b11101101 r
b11101101 s
1I
b0 J
b0 Y
b0 Z
b11110011 =
b11110011 j
b11110011 k
b11110011 2
b11110011 v
b11110011 w
b1010000 G
b1010000 ]
b1010000 ^
0C
b10000000 D
b10000000 a
b10000000 b
09
b11110 :
b11110 n
b11110 o
b11010000 A
b11010000 e
b11010000 f
b1011010000 g
b1000 &
b1000 )
b11 '
b11 *
b11 S
b11 X
b11 \
b11 `
b11 d
b11 i
b11 m
b11 q
b11 u
b11110000 %
b11110000 (
b11110000 R
b11110000 W
b11110000 [
b11110000 _
b11110000 c
b11110000 h
b11110000 l
b11110000 p
b11110000 t
#140
1$
1;
0B
b11110000 #
b11110000 Q
0@
b11110000 N
b11110000 T
b11110000 U
b11110000 V
b11110000 6
b11110000 r
b11110000 s
b11110000 =
b11110000 j
b11110000 k
b11110000 2
b11110000 v
b11110000 w
1F
b0 G
b0 ]
b0 ^
b11110000 D
b11110000 a
b11110000 b
b11110000 :
b11110000 n
b11110000 o
1?
b0 A
b0 e
b0 f
b0 g
b0 '
b0 *
b0 S
b0 X
b0 \
b0 `
b0 d
b0 i
b0 m
b0 q
b0 u
#150
0$
0E
0;
1B
1!
b0 #
b0 Q
1@
b11111000 N
b11111000 T
b11111000 U
b11111000 V
b11101000 6
b11101000 r
b11101000 s
b11111000 =
b11111000 j
b11111000 k
b11111000 2
b11111000 v
b11111000 w
0F
b11110 G
b11110 ]
b11110 ^
1C
b0 D
b0 a
b0 b
19
b0 :
b0 n
b0 o
0?
b10000000 A
b10000000 e
b10000000 f
b11110000000 g
b1000 '
b1000 *
b1000 S
b1000 X
b1000 \
b1000 `
b1000 d
b1000 i
b1000 m
b1000 q
b1000 u
