alu_8bit.sv
module alu_8bit (
    input  logic [7:0] A,          // 8-bit Operand A
    input  logic [7:0] B,          // 8-bit Operand B
    input  logic [3:0] ALU_Sel,    // 4-bit Operation Selector
    output logic [7:0] Result,     // 8-bit Result
    output logic       Z,          // Zero Flag
    output logic       N,          // Negative Flag
    output logic       V           // Overflow Flag
);

    logic [7:0] alu_result;

    // Core ALU Combinational Logic
    always_comb begin
        alu_result = 8'b0; // Default assignment

        case (ALU_Sel)
            4'b0000: alu_result = A + B;          // Addition
            4'b0001: alu_result = A - B;          // Subtraction
            4'b0010: alu_result = A * B;          // Multiplication
            4'b0011: begin                        // Division
                if (B != 0) alu_result = A / B;
                else        alu_result = 8'b0;    // Safe divide-by-zero fallback
            end
            4'b0100: alu_result = A & B;          // Bitwise AND
            4'b0101: alu_result = A | B;          // Bitwise OR
            4'b0110: alu_result = A ^ B;          // Bitwise XOR
            4'b0111: alu_result = A << 1;         // Logical Left Shift
            4'b1000: alu_result = A >> 1;         // Logical Right Shift
            default: alu_result = 8'b0;
        endcase
    end

    // Output assignment
    assign Result = alu_result;

    // Flag calculations
    assign Z = (alu_result == 8'b0);
    assign N = alu_result[7]; // MSB indicates negative in two's complement

    // Overflow logic (V) for signed addition and subtraction
    always_comb begin
        V = 1'b0; 
        if (ALU_Sel == 4'b0000) begin 
            // Add Overflow: (+ A) + (+ B) = (- Res) OR (- A) + (- B) = (+ Res)
            V = (~A[7] & ~B[7] & alu_result[7]) | (A[7] & B[7] & ~alu_result[7]);
        end else if (ALU_Sel == 4'b0001) begin 
            // Sub Overflow: (+ A) - (- B) = (- Res) OR (- A) - (+ B) = (+ Res)
            V = (~A[7] & B[7] & alu_result[7]) | (A[7] & ~B[7] & ~alu_result[7]);
        end
    end

endmodule

tb_alu.sv
module tb_alu;

    // Testbench signals
    logic [7:0] A;
    logic [7:0] B;
    logic [3:0] ALU_Sel;
    logic [7:0] Result;
    logic       Z;
    logic       N;
    logic       V;

    // Instantiate the ALU (Device Under Test)
    alu_8bit dut (
        .A(A),
        .B(B),
        .ALU_Sel(ALU_Sel),
        .Result(Result),
        .Z(Z),
        .N(N),
        .V(V)
    );

    // Test sequence
    initial begin
        // Setup waveform dumping for GTKWave
        $dumpfile("tb_alu.vcd");
        $dumpvars(0, tb_alu);

        $display("Starting ALU Simulation...");
        $display("--------------------------------------------------");
        $display(" A    | B    | Sel | Result | Z | N | V | Operation");
        $display("--------------------------------------------------");

        // 0. Addition (Normal)
        A = 8'd50; B = 8'd25; ALU_Sel = 4'b0000; #10;
        $display("%4d | %4d | %b | %6d | %b | %b | %b | Addition", A, B, ALU_Sel, Result, Z, N, V);

        // 0. Addition (Overflow Trigger: 127 + 1 = 128 -> -128 in signed 8-bit)
        A = 8'd127; B = 8'd1; ALU_Sel = 4'b0000; #10;
        $display("%4d | %4d | %b | %6d | %b | %b | %b | Add (Overflow)", A, B, ALU_Sel, $signed(Result), Z, N, V);

        // 1. Subtraction
        A = 8'd100; B = 8'd20; ALU_Sel = 4'b0001; #10;
        $display("%4d | %4d | %b | %6d | %b | %b | %b | Subtraction", A, B, ALU_Sel, Result, Z, N, V);

        // 2. Multiplication
        A = 8'd10; B = 8'd5; ALU_Sel = 4'b0010; #10;
        $display("%4d | %4d | %b | %6d | %b | %b | %b | Multiplication", A, B, ALU_Sel, Result, Z, N, V);

        // 3. Division
        A = 8'd100; B = 8'd10; ALU_Sel = 4'b0011; #10;
        $display("%4d | %4d | %b | %6d | %b | %b | %b | Division", A, B, ALU_Sel, Result, Z, N, V);

        // 3. Division by Zero
        A = 8'd50; B = 8'd0; ALU_Sel = 4'b0011; #10;
        $display("%4d | %4d | %b | %6d | %b | %b | %b | Div by Zero", A, B, ALU_Sel, Result, Z, N, V);

        // 4. Bitwise AND
        A = 8'b11110000; B = 8'b10101010; ALU_Sel = 4'b0100; #10;
        $display("%b | %b | %b | %b | %b | %b | %b | AND", A, B, ALU_Sel, Result, Z, N, V);

        // 5. Bitwise OR
        A = 8'b11110000; B = 8'b00001111; ALU_Sel = 4'b0101; #10;
        $display("%b | %b | %b | %b | %b | %b | %b | OR", A, B, ALU_Sel, Result, Z, N, V);

        // 6. Bitwise XOR
        A = 8'b11110000; B = 8'b11111111; ALU_Sel = 4'b0110; #10;
        $display("%b | %b | %b | %b | %b | %b | %b | XOR", A, B, ALU_Sel, Result, Z, N, V);

        // 7. Left Shift
        A = 8'b00001111; B = 8'd0; ALU_Sel = 4'b0111; #10;
        $display("%b | ---- | %b | %b | %b | %b | %b | Left Shift", A, ALU_Sel, Result, Z, N, V);

        // 8. Right Shift
        A = 8'b11110000; B = 8'd0; ALU_Sel = 4'b1000; #10;
        $display("%b | ---- | %b | %b | %b | %b | %b | Right Shift", A, ALU_Sel, Result, Z, N, V);

        $display("--------------------------------------------------");
        $display("Simulation Complete.");
        
        $finish; // End simulation
    end

endmodule

sim/tb_alu.vcd
$date
	Thu Jun 18 01:22:28 2026
$end
$version
	Icarus Verilog
$end
$timescale
	1s
$end
$scope module tb_alu $end
$var wire 1 ! Z $end
$var wire 1 " V $end
$var wire 8 # Result [7:0] $end
$var wire 1 $ N $end
$var reg 8 % A [7:0] $end
$var reg 4 & ALU_Sel [3:0] $end
$var reg 8 ' B [7:0] $end
$scope module dut $end
$var wire 8 ( A [7:0] $end
$var wire 4 ) ALU_Sel [3:0] $end
$var wire 8 * B [7:0] $end
$var wire 8 + Result [7:0] $end
$var wire 1 ! Z $end
$var wire 1 $ N $end
$var reg 1 " V $end
$var reg 8 , alu_result [7:0] $end
$upscope $end
$upscope $end
$enddefinitions $end
$comment Show the parameter values. $end
$dumpall
$end
#0
$dumpvars
b1001011 ,
b1001011 +
b11001 *
b0 )
b110010 (
b11001 '
b0 &
b110010 %
0$
b1001011 #
0"
0!
$end
#10
1$
1"
0!
b10000000 #
b10000000 +
b10000000 ,
b1 '
b1 *
b1111111 %
b1111111 (
#20
0$
0"
0!
b1010000 #
b1010000 +
b1010000 ,
b1 &
b1 )
b10100 '
b10100 *
b1100100 %
b1100100 (
#30
0!
b110010 #
b110010 +
b110010 ,
b10 &
b10 )
b101 '
b101 *
b1010 %
b1010 (
#40
0!
b1010 #
b1010 +
b1010 ,
b11 &
b11 )
b1010 '
b1010 *
b1100100 %
b1100100 (
#50
1!
b0 #
b0 +
b0 ,
b0 '
b0 *
b110010 %
b110010 (
#60
1$
0!
b10100000 #
b10100000 +
b10100000 ,
b100 &
b100 )
b10101010 '
b10101010 *
b11110000 %
b11110000 (
#70
0!
b11111111 #
b11111111 +
b11111111 ,
b101 &
b101 )
b1111 '
b1111 *
#80
0$
0!
b1111 #
b1111 +
b1111 ,
b110 &
b110 )
b11111111 '
b11111111 *
#90
0!
b11110 #
b11110 +
b11110 ,
b111 &
b111 )
b0 '
b0 *
b1111 %
b1111 (
#100
0!
b1111000 #
b1111000 +
b1111000 ,
b1000 &
b1000 )
b11110000 %
b11110000 (
